Metadata-Version: 2.1
Name: django-admin-confirm
Version: 1.0.1
Summary: Adds confirmation to Django Admin changes, additions and actions
Home-page: https://github.com/trangpham/django-admin-confirm/
Author: Thu Trang Pham
Author-email: thuutrangpham@gmail.com
License: Apache 2.0
Project-URL: Release Notes, https://github.com/TrangPham/django-admin-confirm/releases
Classifier: Framework :: Django :: 3.2
Classifier: Framework :: Django :: 4.0
Classifier: Framework :: Django :: 4.2
Classifier: Framework :: Django :: 5.2
Classifier: Programming Language :: Python :: 3.8
Classifier: Programming Language :: Python :: 3.9
Classifier: Programming Language :: Python :: 3.10
Classifier: Programming Language :: Python :: 3.11
Classifier: Programming Language :: Python :: 3.12
Classifier: Programming Language :: Python :: 3.13
Classifier: Programming Language :: Python :: 3 :: Only
Requires-Python: >=3.7
License-File: LICENSE
